Workbook

Sheet Assumptions
A1: NORTH — MODEL ASSUMPTIONS (BLUE = input, edit these; yellow = key levers)
A3: TIER PRICING & PER-ORG COGS | G3: SOURCE / NOTE
A4: Handyman price ($/mo, 1 user) | B4: 79 | G4: Pricing-architect ladder (research 2026-07). Under-$100 mandate. vs Jobber Core $39 + Joist/QBO $32-75; undercuts Jobber AI Receptionist add-on alone ($99/mo).
A5: Crew price ($/mo, 5 users incl.) | B5: 169 | G5: vs Jobber Connect $119-169 + Workyard/ClockShark ~$67 + Gusto ~$67 = $250-420/mo stack.
A6: Shop price ($/mo, 10 users incl.) | B6: 299 | G6: vs Jobber Grow $199-349 + NiceJob $75-125 + QBO = ~$570/mo mid stack; ServiceTitan $245-398/tech + $5-50K setup.
A7: North Complete price ($/mo, multi-org) | B7: 499 | G7: Optional 4th rung; ~$199/additional org; sell on inbound only pre-100 orgs.
A8: Extra seat ($/user/mo) | B8: 15 | G8: Flat tiers + cheap marginal seat; contractors hate per-tech metering (ServiceTitan complaint #1).
A9: Annual plan discount (months free) | B9: 2 | G9: Cheapest churn reducer; offer from day one (research: unit economics).
A10: Handyman AI+infra COGS ($/org/mo) | B10: 16 | G10: 300 Nort actions Sonnet-routed ($0.02-0.04/action w/ prompt caching cn-v304) + 30 voice min + infra $3-5. Range $10-25; cap bounds worst case ~$25.
A11: Crew AI+infra COGS ($/org/mo) | B11: 45 | G11: 1,200 actions, Opus routing on money/estimating ($0.05-0.25/action). Range $30-60. Claude API 2026: Sonnet $3/$15, Opus $5/$25 per MTok.
A12: Shop AI+infra COGS ($/org/mo) | B12: 100 | G12: 3,000 actions + nightly debriefs/leak sweeps on Batch API (50% off). Range $70-130.
A13: North Complete AI+infra COGS ($/org/mo) | B13: 180 | G13: Pooled: ~$60-120/org at Shop-level use x ~2.5 orgs.
A14: Payment processing (% of revenue) | B14: 0.04 | G14: Stripe 2.9% + $0.30/charge + 0.7% Billing recurring = ~3.8-4.2% on monthly card billing.
A15: Steady-state monthly churn (LTV calc) | B15: 0.03 | G15: SMB SaaS 3-7%/mo benchmarks; 2.5-3%/mo Y3+ with annual plans + payments attached (research).
... A27: Erik hourly value ($/hr) | B27: 150 | G27: Erik's billable electrician rate — opportunity cost of every North hour.
A30: BY-YEAR INPUTS | B30: Y1 | C30: Y2 | D30: Y3 | E30: Y4 | F30: Y5 | G30: SOURCE / NOTE
A31: Monthly churn % | B31: 0.05 | C31: 0.04 | D31: 0.035 | E31: 0.03 | F31: 0.0275 | G31: Model: 5%/mo Y1 (unproven onboarding) -> 3.5% -> 2.5-3% with annual plans (research churn benchmarks). If churn runs 6%/mo, national numbers roughly halve.
A32: Blended CAC ($/gross add) | B32: 75 | C32: 175 | D32: 200 | E32: 250 | F32: 275 | G32: Y1 mostly Erik network; Y2+ referral-dominant; drifts up as organic/paid mix in. Referral $150-225, paid $350-700.
A33: Tools / insurance / legal ($/yr) | B33: 8000 | C33: 14000 | D33: 30000 | E33: 60000 | F33: 90000 | G33: E&O+cyber $2-6K/yr, ToS/privacy $2-5K, trademark $1.5-3K, helpdesk/status page; scales with headcount.
A34: SOC 2 ($/yr) | B34: 0 | C34: 0 | D34: 45000 | E34: 32000 | F34: 32000 | G34: Trigger ~$500K-1M ARR = Y3. First-year all-in $30-65K (platform $10-15K + audit $15-50K); renewals +15-25% creep.
A35: Engineers (FTE) | B35: 0 | C35: 0 | D35: 1 | E35: 3 | F35: 4 | G35: Hire #1 at ~$400-600K ARR (Y3); Y4 base team 6-10 people total (research adoption model).
A36: Growth/CS (FTE) | B36: 0 | C36: 0 | D36: 0 | E36: 1 | F36: 1 | G36: At ~1,000 customers.
A37: Founder draw ($/yr) | B37: 0 | C37: 0 | D37: 60000 | E37: 120000 | F37: 150000 | G37: Y1-2 = $0 (ET Electric funds Erik); draws begin when North is the majority job.
A38: Erik hours/week on North | B38: 15 | C38: 25 | D38: 40 | E38: 50 | F38: 50 | G38: Y1 10-20 hrs/wk on top of ET Electric (research); Y3+ assumes the month-9-12 go decision was YES.
A40: ADOPTION — PAYING ORGS AT YEAR END (base case) | B40: Y1 | C40: Y2 | D40: Y3 | E40: Y4 | F40: Y5 | G40: SOURCE / NOTE
A41: Handyman orgs | B41: 10 | C41: 100 | D41: 600 | E41: 1600 | F41: 3400 | G41: Mix shifts handyman-heavy at national scale (research: blended ARPU drifts down as handyman mix grows).
A42: Crew orgs | B42: 17 | C42: 105 | D42: 450 | E42: 1050 | F42: 2000 | G42: Y1 skews Crew/Shop: local adopters are the licensed referral network Erik knows.
A43: Shop orgs | B43: 8 | C43: 40 | D43: 130 | E43: 300 | F43: 520 | G43: Licensed, draw-billing C-10-class shops.
A44: North Complete orgs | B44: 0 | C44: 5 | D44: 20 | E44: 50 | F44: 80 | G44: Inbound only.
A45: Total orgs (EOY) | B45: =SUM(B41:B44) -> 35 | C45: =SUM(C41:C44) -> 250 | D45: =SUM(D41:D44) -> 1200 | E45: =SUM(E41:E44) -> 3000 | F45: =SUM(F41:F44) -> 6000 | G45: Research bases: Y1 25-60 (exit ARR $35-85K); Y2 base 250; Y3 1,000-2,500; Y4 2,500-5,000; Y5 5,000-10,000 bootstrapped.

Sheet Tiers
A1: PER-TIER UNIT ECONOMICS (all formulas off Assumptions)
B3: Handyman | C3: Crew | D3: Shop | E3: North Complete | G3: NOTE
A4: Price ($/mo) | B4: =Assumptions!$B$4 -> 79 | C4: =Assumptions!$B$5 -> 169 | D4: =Assumptions!$B$6 -> 299 | E4: =Assumptions!$B$7 -> 499 | G4: Flat, seats included (1/5/10), +$15/extra seat.
A5: AI + infra COGS ($/mo) | B5: =Assumptions!$B$10 -> 16 | C5: =Assumptions!$B$11 -> 45 | D5: =Assumptions!$B$12 -> 100 | E5: =Assumptions!$B$13 -> 180 | G5: Nort actions + voice + Supabase/Vercel marginal.
A6: Payment fees ($/mo) | B6: =B4*Assumptions!$B$14 -> 3.16 | C6: =C4*Assumptions!$B$14 -> 6.76 | D6: =D4*Assumptions!$B$14 -> 11.96 | E6: =E4*Assumptions!$B$14 -> 19.96 | G6: ~4% of revenue (Stripe + Billing).
A7: Total COGS ($/mo) | B7: =B5+B6 -> 19.16 | C7: =C5+C6 -> 51.76 | D7: =D5+D6 -> 111.96 | E7: =E5+E6 -> 199.96
A8: Gross margin ($/mo) | B8: =B4-B7 -> 59.84 | C8: =C4-C7 -> 117.24 | D8: =D4-D7 -> 187.04 | E8: =E4-E7 -> 299.04
A9: Gross margin (%) | B9: =B8/B4 -> 0.75746835 | C9: =C8/C4 -> 0.69372781 | D9: =D8/D4 -> 0.62555184 | E9: =E8/E4 -> 0.59927856 | G9: Incl. payment fees. Excl. fees, research expects ~80% / ~70-72% / ~65% / 60-70%. AI-native SaaS runs 55-70% today; do not promise 80%.
A10: Avg customer lifetime (months) | B10: =1/Assumptions!$B$15 -> 33.333333 | C10: =1/Assumptions!$B$15 -> 33.333333 | D10: =1/Assumptions!$B$15 -> 33.333333 | E10: =1/Assumptions!$B$15 -> 33.333333 | G10: 1 / steady-state monthly churn (3%/mo -> ~33 months).
A11: LTV — lifetime gross margin ($) | B11: =B8*B10 -> 1994.6667 | C11: =C8*C10 -> 3908 | D11: =D8*D10 -> 6234.6667 | E11: =E8*E10 -> 9968
A12: CAC — referral channel ($) | B12: =Assumptions!$B$16 -> 185 | C12: =Assumptions!$B$16 -> 185 | D12: =Assumptions!$B$16 -> 185 | E12: =Assumptions!$B$16 -> 185 | G12: The priced channel (QR engine, built).
A13: CAC payback (months) | B13: =B12/B8 -> 3.0915775 | C13: =C12/C8 -> 1.5779597 | D13: =D12/D8 -> 0.98909324 | E13: =E12/E8 -> 0.61864633 | G13: Referral payback 2-3 months per research; paid-ads payback 8-9 months.
A14: LTV : CAC | B14: =B11/B12 -> 10.781982 | C14: =C11/C12 -> 21.124324 | D14: =D11/D12 -> 33.700901 | E14: =E11/E12 -> 53.881081 | G14: Healthy floor is 3x; referral is exceptional — productize the QR engine before buying ads.

Sheet Model_5yr
A1: 5-YEAR BASE CASE — BOOTSTRAPPED (all formulas; inputs live on Assumptions)
B3: Y1 | C3: Y2 | D3: Y3 | E3: Y4 | F3: Y5 | H3: NOTE
A4: CUSTOMERS (end of year)
A5: Handyman | B5: =Assumptions!B41 -> 10 | C5: =Assumptions!C41 -> 100 | D5: =Assumptions!D41 -> 600 | E5: =Assumptions!E41 -> 1600 | F5: =Assumptions!F41 -> 3400
A6: Crew | B6: =Assumptions!B42 -> 17 | C6: =Assumptions!C42 -> 105 | D6: =Assumptions!D42 -> 450 | E6: =Assumptions!E42 -> 1050 | F6: =Assumptions!F42 -> 2000
A7: Shop | B7: =Assumptions!B43 -> 8 | C7: =Assumptions!C43 -> 40 | D7: =Assumptions!D43 -> 130 | E7: =Assumptions!E43 -> 300 | F7: =Assumptions!F43 -> 520
A8: North Complete | B8: =Assumptions!B44 -> 0 | C8: =Assumptions!C44 -> 5 | D8: =Assumptions!D44 -> 20 | E8: =Assumptions!E44 -> 50 | F8: =Assumptions!F44 -> 80
A9: Total orgs (EOY) | B9: =SUM(B5:B8) -> 35 | C9: =SUM(C5:C8) -> 250 | D9: =SUM(D5:D8) -> 1200 | E9: =SUM(E5:E8) -> 3000 | F9: =SUM(F5:F8) -> 6000 | H9: Base: 35 / 250 / 1,200 / 3,000 / 6,000.
A10: Average orgs in year | B10: =(0+B9)/2 -> 17.5 | C10: =(B9+C9)/2 -> 142.5 | D10: =(C9+D9)/2 -> 725 | E10: =(D9+E9)/2 -> 2100 | F10: =(E9+F9)/2 -> 4500 | H10: Start-of-Y1 = 0 paying strangers (Erik + Tahoe Deck are internal).
A12: REVENUE
A13: Exit MRR ($/mo) | B13: =B5*Assumptions!$B$4+B6*Assumptions!$B$5+B7*Assumptions!$B$6+B8*Assumptions!$B$7 -> 6055 | C13: =C5*Assumptions!$B$4+C6*Assumptions!$B$5+C7*Assumptions!$B$6+C8*Assumptions!$B$7 -> 40100 | D13: =D5*Assumptions!$B$4+D6*Assumptions!$B$5+D7*Assumptions!$B$6+D8*Assumptions!$B$7 -> 172300 | E13: =E5*Assumptions!$B$4+E6*Assumptions!$B$5+E7*Assumptions!$B$6+E8*Assumptions!$B$7 -> 418500 | F13: =F5*Assumptions!$B$4+F6*Assumptions!$B$5+F7*Assumptions!$B$6+F8*Assumptions!$B$7 -> 802000
A14: Exit ARR (run-rate) | B14: =B13*12 -> 72660 | C14: =C13*12 -> 481200 | D14: =D13*12 -> 2067600 | E14: =E13*12 -> 5022000 | F14: =F13*12 -> 9624000 | H14: Research bands: Y1 $35-85K; Y2 $200-540K; Y4 $3.2-6.3M; Y5 $6-12M bootstrapped.
A15: Blended ARPU (EOY, $/mo) | B15: =B13/B9 -> 173 | C15: =C13/C9 -> 160.4 | D15: =D13/D9 -> 143.58333 | E15: =E13/E9 -> 139.5 | F15: =F13/F9 -> 133.66667 | H15: Higher than the research $105-115 anchor because the architect ladder prices higher; mix-shift pulls it down over time.
A16: Recognized revenue ($/yr) | B16: =(0+B13)/2*12 -> 36330 | C16: =(B13+C13)/2*12 -> 276930 | D16: =(C13+D13)/2*12 -> 1274400 | E16: =(D13+E13)/2*12 -> 3544800 | F16: =(E13+F13)/2*12 -> 7323000 | H16: Average of opening and closing MRR x 12.
A18: COGS
A19: AI + infra COGS | B19: =12*((B5/2)*Assumptions!$B$10+(B6/2)*Assumptions!$B$11+(B7/2)*Assumptions!$B$12+(B8/2)*Assumptions!$B$13) -> 10350 | C19: =12*(((B5+C5)/2)*Assumptions!$B$10+((B6+C6)/2)*Assumptions!$B$11+((B7+C7)/2)*Assumptions!$B$12+((B8+C8)/2)*Assumptions!$B$13) -> 77700 | D19: =12*(((C5+D5)/2)*Assumptions!$B$10+((C6+D6)/2)*Assumptions!$B$11+((C7+D7)/2)*Assumptions!$B$12+((C8+D8)/2)*Assumptions!$B$13) -> 346050 | E19: =12*(((D5+E5)/2)*Assumptions!$B$10+((D6+E6)/2)*Assumptions!$B$11+((D7+E7)/2)*Assumptions!$B$12+((D8+E8)/2)*Assumptions!$B$13) -> 949800 | F19: =12*(((E5+F5)/2)*Assumptions!$B$10+((E6+F6)/2)*Assumptions!$B$11+((E7+F7)/2)*Assumptions!$B$12+((E8+F8)/2)*Assumptions!$B$13) -> 1935900 | H19: Avg orgs per tier x per-tier COGS x 12. AI is the dominant COGS line.
A20: Payment processing fees | B20: =B16*Assumptions!$B$14 -> 1453.2 | C20: =C16*Assumptions!$B$14 -> 11077.2 | D20: =D16*Assumptions!$B$14 -> 50976 | E20: =E16*Assumptions!$B$14 -> 141792 | F20: =F16*Assumptions!$B$14 -> 292920
A21: Total COGS | B21: =B19+B20 -> 11803.2 | C21: =C19+C20 -> 88777.2 | D21: =D19+D20 -> 397026 | E21: =E19+E20 -> 1091592 | F21: =F19+F20 -> 2228820
A22: Gross profit | B22: =B16-B21 -> 24526.8 | C22: =C16-C21 -> 188152.8 | D22: =D16-D21 -> 877374 | E22: =E16-E21 -> 2453208 | F22: =F16-F21 -> 5094180
A23: Gross margin % | B23: =B22/B16 -> 0.67511148 | C23: =C22/C16 -> 0.67942368 | D23: =D22/D16 -> 0.68846045 | E23: =E22/E16 -> 0.69205823 | F23: =F22/F16 -> 0.69564113 | H23: Target 65-72% Y1-2 improving to 75%+ (research); classic SaaS 75-80%, AI-native 55-70%.
A25: OPEX
A26: Support FTE | B26: =IF(B9<Assumptions!$B$21,0,ROUNDUP(B10/Assumptions!$B$20,0)) -> 0 | C26: =IF(C9<Assumptions!$B$21,0,ROUNDUP(C10/Assumptions!$B$20,0)) -> 1 | D26: =IF(D9<Assumptions!$B$21,0,ROUNDUP(D10/Assumptions!$B$20,0)) -> 3 | E26: =IF(E9<Assumptions!$B$21,0,ROUNDUP(E10/Assumptions!$B$20,0)) -> 6 | F26: =IF(F9<Assumptions!$B$21,0,ROUNDUP(F10/Assumptions!$B$20,0)) -> 13 | H26: Formula: 0 until the 200-customer trigger, then avg orgs / 350 (SaaStr 1:250-500).
A27: Support cost | B27: =B26*Assumptions!$B$22 -> 0 | C27: =C26*Assumptions!$B$22 -> 65000 | D27: =D26*Assumptions!$B$22 -> 195000 | E27: =E26*Assumptions!$B$22 -> 390000 | F27: =F26*Assumptions!$B$22 -> 845000
A28: Engineers (FTE) | B28: =Assumptions!B35 -> 0 | C28: =Assumptions!C35 -> 0 | D28: =Assumptions!D35 -> 1 | E28: =Assumptions!E35 -> 3 | F28: =Assumptions!F35 -> 4
A29: Engineering cost | B29: =B28*Assumptions!$B$23 -> 0 | C29: =C28*Assumptions!$B$23 -> 0 | D29: =D28*Assumptions!$B$23 -> 140000 | E29: =E28*Assumptions!$B$23 -> 420000 | F29: =F28*Assumptions!$B$23 -> 560000
A30: Growth/CS (FTE) | B30: =Assumptions!B36 -> 0 | C30: =Assumptions!C36 -> 0 | D30: =Assumptions!D36 -> 0 | E30: =Assumptions!E36 -> 1 | F30: =Assumptions!F36 -> 1
A31: Growth/CS cost | B31: =B30*Assumptions!$B$24 -> 0 | C31: =C30*Assumptions!$B$24 -> 0 | D31: =D30*Assumptions!$B$24 -> 0 | E31: =E30*Assumptions!$B$24 -> 100000 | F31: =F30*Assumptions!$B$24 -> 100000
A32: Founder draw | B32: =Assumptions!B37 -> 0 | C32: =Assumptions!C37 -> 0 | D32: =Assumptions!D37 -> 60000 | E32: =Assumptions!E37 -> 120000 | F32: =Assumptions!F37 -> 150000
A33: Tools / insurance / legal | B33: =Assumptions!B33 -> 8000 | C33: =Assumptions!C33 -> 14000 | D33: =Assumptions!D33 -> 30000 | E33: =Assumptions!E33 -> 60000 | F33: =Assumptions!F33 -> 90000
A34: Pen test | B34: =Assumptions!$B$25 -> 10000 | C34: =Assumptions!$B$25 -> 10000 | D34: =Assumptions!$B$25 -> 10000 | E34: =Assumptions!$B$25 -> 10000 | F34: =Assumptions!$B$25 -> 10000
A35: SOC 2 | B35: =Assumptions!B34 -> 0 | C35: =Assumptions!C34 -> 0 | D35: =Assumptions!D34 -> 45000 | E35: =Assumptions!E34 -> 32000 | F35: =Assumptions!F34 -> 32000 | H35: Lands Y3 (~$500K-1M ARR trigger).
A36: Churned orgs (during year) | B36: =B10*Assumptions!B31*12 -> 10.5 | C36: =C10*Assumptions!C31*12 -> 68.4 | D36: =D10*Assumptions!D31*12 -> 304.5 | E36: =E10*Assumptions!E31*12 -> 756 | F36: =F10*Assumptions!F31*12 -> 1485
A37: Gross new orgs added | B37: =B9+B36 -> 45.5 | C37: =C9-B9+C36 -> 283.4 | D37: =D9-C9+D36 -> 1254.5 | E37: =E9-D9+E36 -> 2556 | F37: =F9-E9+F36 -> 4485
A38: S&M / CAC spend | B38: =B37*Assumptions!B32 -> 3412.5 | C38: =C37*Assumptions!C32 -> 49595 | D38: =D37*Assumptions!D32 -> 250900 | E38: =E37*Assumptions!E32 -> 639000 | F38: =F37*Assumptions!F32 -> 1233375 | H38: Gross adds x blended CAC. Referral engine is the dominant channel through Y2.
A39: Other G&A | B39: =B16*Assumptions!$B$26 -> 1816.5 | C39: =C16*Assumptions!$B$26 -> 13846.5 | D39: =D16*Assumptions!$B$26 -> 63720 | E39: =E16*Assumptions!$B$26 -> 177240 | F39: =F16*Assumptions!$B$26 -> 366150
A40: Total opex | B40: =B27+B29+B31+B32+B33+B34+B35+B38+B39 -> 23229 | C40: =C27+C29+C31+C32+C33+C34+C35+C38+C39 -> 152441.5 | D40: =D27+D29+D31+D32+D33+D34+D35+D38+D39 -> 794620 | E40: =E27+E29+E31+E32+E33+E34+E35+E38+E39 -> 1948240 | F40: =F27+F29+F31+F32+F33+F34+F35+F38+F39 -> 3386525
A42: OPERATING PROFIT | B42: =B22-B40 -> 1297.8 | C42: =C22-C40 -> 35711.3 | D42: =D22-D40 -> 82754 | E42: =E22-E40 -> 504968 | F42: =F22-F40 -> 1707655 | H42: Research bands: Y1 ~breakeven to +$30K; Y2 -$20K to +$80K; Y3-4 margin -10% to +15%; Y5 10-25%.
A43: Operating margin % | B43: =B42/B16 -> 0.035722543 | C43: =C42/C16 -> 0.12895425 | D43: =D42/D16 -> 0.064935656 | E43: =E42/E16 -> 0.14245317 | F43: =F42/F16 -> 0.23319063
A45: Team size (incl. Erik) | B45: =B26+B28+B30+1 -> 1 | C45: =C26+C28+C30+1 -> 2 | D45: =D26+D28+D30+1 -> 5 | E45: =E26+E28+E30+1 -> 11 | F45: =F26+F28+F30+1 -> 19 | H45: Research Y5 base: 12-20 staff.
A46: Erik hours/week | B46: =Assumptions!B38 -> 15 | C46: =Assumptions!C38 -> 25 | D46: =Assumptions!D38 -> 40 | E46: =Assumptions!E38 -> 50 | F46: =Assumptions!F38 -> 50 | H46: THE governing decision. 5-10 hrs/wk = ~10-org side business; 15-20 = regional sweet spot; 40+ only after ~$20K MRR at <3% churn.

Sheet Scenarios
A1: YEAR-5 SCENARIOS (levers in blue/yellow; everything else recomputes)
B3: Conservative | C3: Base | D3: Aggressive | F3: NOTE
A4: Customer multiplier (x base Y5 orgs) | B4: 0.5 | C4: 1 | D4: 1.6 | F4: Conservative ~ churn runs 5-6%/mo / referral stalls: research says national numbers roughly halve.
A5: ARPU multiplier | B5: 0.95 | C5: 1 | D5: 1.05 | F5: Price pressure down (Jobber ships comparable AI) vs annual-mix up.
A6: Gross-margin delta (pts) | B6: -0.04 | C6: 0 | D6: 0.02 | F6: AI COGS blowout vs model-price declines + better caching (treat declines as upside, not plan).
A7: Fixed share of opex (all scenarios) | B7: 0.4 | F7: Share of Y5 base opex that does not scale with customer count.
A9: Y5 customers (EOY) | B9: =Model_5yr!$F$9*B4 -> 3000 | C9: =Model_5yr!$F$9*C4 -> 6000 | D9: =Model_5yr!$F$9*D4 -> 9600
A10: Y5 exit ARR | B10: =Model_5yr!$F$14*B4*B5 -> 4571400 | C10: =Model_5yr!$F$14*C4*C5 -> 9624000 | D10: =Model_5yr!$F$14*D4*D5 -> 16168320
A11: Y5 recognized revenue | B11: =Model_5yr!$F$16*B4*B5 -> 3478425 | C11: =Model_5yr!$F$16*C4*C5 -> 7323000 | D11: =Model_5yr!$F$16*D4*D5 -> 12302640
A12: Y5 gross margin % | B12: =Model_5yr!$F$23+B6 -> 0.65564113 | C12: =Model_5yr!$F$23+C6 -> 0.69564113 | D12: =Model_5yr!$F$23+D6 -> 0.71564113
A13: Y5 gross profit | B13: =B11*B12 -> 2280598.5 | C13: =C11*C12 -> 5094180 | D13: =D11*D12 -> 8804275.2
A14: Y5 opex | B14: =Model_5yr!$F$40*($B$7+(1-$B$7)*B4) -> 2370567.5 | C14: =Model_5yr!$F$40*($B$7+(1-$B$7)*C4) -> 3386525 | D14: =Model_5yr!$F$40*($B$7+(1-$B$7)*D4) -> 4605674
A15: Y5 OPERATING PROFIT | B15: =B13-B14 -> -89969 | C15: =C13-C14 -> 1707655 | D15: =D13-D14 -> 4198601.2
A16: Y5 operating margin % | B16: =B15/B11 -> -0.025864867 | C16: =C15/C11 -> 0.23319063 | D16: =D15/D11 -> 0.34127644
A18: Funded variant (not modeled here): $3-6M raise at Y3 with paid-CAC payback proven <12 mo -> 8,000-15,000 customers, $10-19M ARR by Y4, burning $150-400K/mo, ~25-35% cumulative dilution (research adoption model).

Sheet Customer_ROI
A1: PER-SHOP ROI — solo licensed trade, base case (blue = sourced assumptions)
A3: INPUTS | F3: SOURCE
A4: Shop annual revenue ($) | B4: 300000 | F4: Research ROI-stack reference case: solo licensed electrician, $300K/yr.
A5: Billable rate ($/hr) | B5: 125 | F5: $100-150/hr solo licensed trade.
A6: Admin hours saved per week | B6: 4.5 | F6: UK trades ~7 hrs/wk paperwork (Powered Now); Tradify survey ~6 hrs/wk saved; modeled conservatively at 3-6 -> 4.5.
A7: Share of saved hours converted to billable | B7: 0.3333 | F7: Honest split: 1/3 becomes billed work, 2/3 becomes evenings back (real value, not revenue).
A8: Working weeks per year | B8: 48
A9: Leak recovery (% of revenue) | B9: 0.02 | F9: Firms bill only ~90-95% of delivered hours (SPI); leakage 1-5% of revenue benchmarks; modeled 1-3% -> 2%.
A10: DSO days accelerated | B10: 30 | F10: 82% of contractors wait >30 days (Rabbet); online-pay invoices paid up to 4x faster (QuickBooks).
A11: Cost of money (%/yr) | B11: 0.12 | F11: Contractor credit-line rate.
A13: VALUE RECOVERED ($/yr)
A14: Billable hours recovered per year | B14: =B6*B7*B8 -> 71.9928
A15: Value of billable hours | B15: =B14*B5 -> 8999.1 | F15: ~$5-14K/yr band in research.
A16: Evenings-back hours (unpriced) | B16: =B6*(1-B7)*B8 -> 144.0072 | F16: ~150-250 hrs/yr of life returned — never shows in GDP; arguably the point.
A17: Leak recovery | B17: =B4*B9 -> 6000 | F17: $3-9K/yr band.
A18: Cash-flow / DSO value | B18: =B4*B10/365*B11 -> 2958.9041 | F18: $1-4K/yr band.
A19: TOTAL recovered per year | B19: =B15+B17+B18 -> 17958.004 | F19: Research total: $9-27K/yr.
A21: ROI VS TIER COST | B21: Handyman | C21: Crew | D21: Shop
A22: Annual tier cost | B22: =Assumptions!$B$4*12 -> 948 | C22: =Assumptions!$B$5*12 -> 2028 | D22: =Assumptions!$B$6*12 -> 3588 | F22: Research: ROI 3-12x, payback 1-3 months of value. A $300K shop belongs on Crew/Shop — quote the Crew multiple, not Handyman.
A23: ROI multiple (value / cost) | B23: =$B$19/B22 -> 18.943042 | C23: =$B$19/C22 -> 8.8550316 | D23: =$B$19/D22 -> 5.0050179
A24: Payback (months of value) | B24: =B22/($B$19/12) -> 0.63347797 | C24: =C22/($B$19/12) -> 1.3551617 | D24: =D22/($B$19/12) -> 2.3975938
A26: NOT PRICED IN: estimating time saved 2-5 hrs/wk (detailed estimate = 1-2 hrs; outsourced estimates $150-1,000 each); faster-quote win-rate (industry lore, unsourced); GPS timeclock payroll savings 2-5% of gross payroll (vendor-sourced, soft). HONESTY FLAGS: savings figures come substantially from vendor surveys (Tradify, QuickBooks) with selection bias; hour-to-dollar conversion depends entirely on backlog — full backlog converts at ~100%, no demand converts at ~0% and just returns evenings.
